idkgens/__init__.py
idkgens/_version.py
idkgens/insight.py
idkgens/io.py
cdl_idk_gens-0.3.5.dist-info/METADATA
cdl_idk_gens-0.3.5.dist-info/WHEEL
cdl_idk_gens-0.3.5.dist-info/top_level.txt
cdl_idk_gens-0.3.5.dist-info/RECORD
